flimit/memory.py
flimit/time.py
flimit-1.0.0.dist-info/WHEEL
flimit-1.0.0.dist-info/METADATA
flimit-1.0.0.dist-info/RECORD
