Metadata-Version: 2.1
Name: flimit
Version: 1.0.0
Summary: Limit time and memory usage from a function
Home-page: https://github.com/fortierq/flimit
License: MIT
Keywords: limit,time,memory,function
Author: Quentin Fortier
Author-email: qpfortier@gmail.com
Requires-Python: >=3.7,<4.0
Classifier: License :: OSI Approved :: MIT License
Classifier: Programming Language :: Python :: 3
Classifier: Programming Language :: Python :: 3.7
Classifier: Programming Language :: Python :: 3.8
Classifier: Programming Language :: Python :: 3.9
Requires-Dist: psutil (>=5.8.0,<6.0.0)
Project-URL: Repository, https://github.com/fortierq/flimit
